{
  "timestamp": "2023.10.11.23:01.33644736",
  "Ext_V2X_Tx_PDU": {
    "ver": 1,
    "e_payload_type": 0,
    "psid": 5271,
    "tx_power": 20,
    "e_signer_id": 0,
    "e_priority": 0,
    "magic_num": 62194,
    "u.config_cv2x": {
      "transmitter_profile_id": 100,
      "peer_l2id": 0
    },
    "v2x_msg": {
      "length": 1384,
      "data": {
        "eDeviceType": 1,
        "eTeleCommType": 30,
        "unDeviceId": 71,
        "ulTimeStamp": 0,
        "eServiceId": 4,
        "eActionType": 1,
        "eRegionId": 1,
        "ePayloadType": 1,
        "eCommId": 1,
        "ulPayloadLength": 1320,
        "messageFrame": {
          "coreData": {
            "msgCnt": 76,
            "rx_msg_cnt": 71,
            "lat": 374178098.0,
            "long": 1266109196.0,
            "signal": 2.0,
            "heading": 28720.0,
            "velocity": 424.0
          }
        },
        "path": [
          {
            "x": -4070.9482369326893,
            "y": 3822.0780204824305
          },
          {
            "x": -4068.948262080048,
            "y": 3822.08804987921
          },
          {
            "x": -4066.948287237306,
            "y": 3822.0980812498747
          },
          {
            "x": -4064.9483123945633,
            "y": 3822.1081126205395
          },
          {
            "x": -4062.948337551821,
            "y": 3822.1181439912043
          },
          {
            "x": -4060.9483627090785,
            "y": 3822.128175361869
          },
          {
            "x": -4058.9483878663364,
            "y": 3822.138206732534
          },
          {
            "x": -4056.4484193129083,
            "y": 3822.1507459458653
          },
          {
            "x": -4054.4484444701657,
            "y": 3822.16077731653
          },
          {
            "x": -4052.4484696274235,
            "y": 3822.170808687195
          },
          {
            "x": -4050.448494784681,
            "y": 3822.1808400578598
          },
          {
            "x": -4048.4485199419382,
            "y": 3822.1908714285246
          },
          {
            "x": -4046.448545099196,
            "y": 3822.2009027991894
          },
          {
            "x": -4044.448570264049,
            "y": 3822.210935683855
          },
          {
            "x": -4041.948601742595,
            "y": 3822.2234812702727
          },
          {
            "x": -4039.9486269254317,
            "y": 3822.2335177394066
          },
          {
            "x": -4037.9559666506925,
            "y": 3822.062330621094
          },
          {
            "x": -4035.9633063759534,
            "y": 3821.8911435027812
          },
          {
            "x": -4033.970646101214,
            "y": 3821.719956384469
          },
          {
            "x": -4031.9779858264747,
            "y": 3821.5487692661563
          },
          {
            "x": -4029.9853255517355,
            "y": 3821.377582147844
          },
          {
            "x": -4027.4945002083114,
            "y": 3821.163598249953
          },
          {
            "x": -4025.5018399335722,
            "y": 3820.9924111316404
          },
          {
            "x": -4023.509179658833,
            "y": 3820.821224013328
          },
          {
            "x": -4021.516519384094,
            "y": 3820.6500368950155
          },
          {
            "x": -4019.5238591093544,
            "y": 3820.4788497767026
          },
          {
            "x": -4017.531198834615,
            "y": 3820.30766265839
          },
          {
            "x": -4015.538538559876,
            "y": 3820.1364755400778
          },
          {
            "x": -4013.047713216452,
            "y": 3819.9224916421867
          },
          {
            "x": -4011.055052941713,
            "y": 3819.7513045238743
          },
          {
            "x": -4009.0623926669737,
            "y": 3819.580117405562
          },
          {
            "x": -4007.0697323922345,
            "y": 3819.4089302872494
          },
          {
            "x": -4005.077072117495,
            "y": 3819.2377431689365
          },
          {
            "x": -4003.082178219508,
            "y": 3819.121331893252
          },
          {
            "x": -4001.0821957632543,
            "y": 3819.129708925998
          },
          {
            "x": -3998.5822176929373,
            "y": 3819.1401802169303
          },
          {
            "x": -3996.5822352366836,
            "y": 3819.1485572496763
          },
          {
            "x": -3994.58225278043,
            "y": 3819.1569342824223
          },
          {
            "x": -3992.582270324176,
            "y": 3819.1653113151683
          },
          {
            "x": -3990.5822878720014,
            "y": 3819.1736893215966
          },
          {
            "x": -3988.582305428276,
            "y": 3819.182069344849
          },
          {
            "x": -3986.5823229845505,
            "y": 3819.1904493681013
          },
          {
            "x": -3984.0823449298937,
            "y": 3819.2009243971665
          },
          {
            "x": -3982.082362486168,
            "y": 3819.209304420419
          },
          {
            "x": -3980.0823800424428,
            "y": 3819.217684443671
          },
          {
            "x": -3978.0823976078836,
            "y": 3819.2260666542975
          },
          {
            "x": -3976.0824151764446,
            "y": 3819.2344496092564
          },
          {
            "x": -3974.082432745005,
            "y": 3819.242832564215
          },
          {
            "x": -3971.582454705706,
            "y": 3819.2533112579135
          },
          {
            "x": -3971.582454705706,
            "y": 3819.2533112579135
          }
        ]
      }
    }
  }
}