{
  "timestamp": "2023.10.11.22:42.51573086",
  "Ext_V2X_Tx_PDU": {
    "ver": 1,
    "e_payload_type": 0,
    "psid": 5272,
    "tx_power": 20,
    "e_signer_id": 0,
    "e_priority": 0,
    "magic_num": 62450,
    "u.config_cv2x": {
      "transmitter_profile_id": 100,
      "peer_l2id": 0
    },
    "v2x_msg": {
      "length": 57608,
      "data": {
        "eDeviceType": 1,
        "eTeleCommType": 30,
        "unDeviceId": 72,
        "ulTimeStamp": 0,
        "eServiceId": 4,
        "eActionType": 1,
        "eRegionId": 1,
        "ePayloadType": 1,
        "eCommId": 1,
        "ulPayloadLength": 57544,
        "messageFrame": {
          "coreData": {
            "msgCnt": 33,
            "rx_msg_cnt": 51,
            "lat": 374180014.0,
            "long": 1266132810.0,
            "signal": 0.0,
            "heading": 21440.0,
            "velocity": 213.0
          }
        },
        "path": [
          {
            "x": -3847.769873187697,
            "y": 3844.6090072821444
          },
          {
            "x": -3848.2698271969953,
            "y": 3844.6022257936033
          },
          {
            "x": -3848.7697812062934,
            "y": 3844.595444305062
          },
          {
            "x": -3849.269735215591,
            "y": 3844.5886628165204
          },
          {
            "x": -3849.769689224889,
            "y": 3844.5818813279793
          },
          {
            "x": -3850.2696432341872,
            "y": 3844.575099839438
          },
          {
            "x": -3850.7695972434854,
            "y": 3844.5683183508963
          },
          {
            "x": -3851.2695512527835,
            "y": 3844.5615368623553
          },
          {
            "x": -3851.7695052623017,
            "y": 3844.5547553900465
          },
          {
            "x": -3852.269488618415,
            "y": 3844.550675732014
          },
          {
            "x": -3852.7694751211957,
            "y": 3844.547001900619
          },
          {
            "x": -3853.2694616239764,
            "y": 3844.543328069224
          },
          {
            "x": -3853.7694481267567,
            "y": 3844.5396542378294
          },
          {
            "x": -3854.2694346295375,
            "y": 3844.535980406434
          },
          {
            "x": -3854.7694211323183,
            "y": 3844.5323065750395
          },
          {
            "x": -3855.269407635099,
            "y": 3844.5286327436447
          },
          {
            "x": -3855.7693941378798,
            "y": 3844.5249589122495
          },
          {
            "x": -3856.2693806406605,
            "y": 3844.521285080855
          },
          {
            "x": -3856.7693671434413,
            "y": 3844.5176112494596
          },
          {
            "x": -3857.269353646222,
            "y": 3844.513937418065
          },
          {
            "x": -3857.769340149003,
            "y": 3844.51026358667
          },
          {
            "x": -3858.269326651783,
            "y": 3844.506589755275
          },
          {
            "x": -3858.769313154564,
            "y": 3844.50291592388
          },
          {
            "x": -3859.2692996573446,
            "y": 3844.4992420924855
          },
          {
            "x": -3859.7692861601254,
            "y": 3844.4955682610903
          },
          {
            "x": -3860.269272662906,
            "y": 3844.4918944296955
          },
          {
            "x": -3860.769259165687,
            "y": 3844.488220598301
          },
          {
            "x": -3861.2692456684676,
            "y": 3844.4845467669056
          },
          {
            "x": -3861.7692321712484,
            "y": 3844.480872935511
          },
          {
            "x": -3862.269218674029,
            "y": 3844.477199104116
          },
          {
            "x": -3862.7692051768095,
            "y": 3844.473525272721
          },
          {
            "x": -3863.26919167959,
            "y": 3844.469851441326
          },
          {
            "x": -3863.769178182371,
            "y": 3844.466177609931
          },
          {
            "x": -3864.2691646851517,
            "y": 3844.4625037785363
          },
          {
            "x": -3864.7691511879325,
            "y": 3844.4588299471416
          },
          {
            "x": -3865.2691376907133,
            "y": 3844.4551561157464
          },
          {
            "x": -3865.769124193494,
            "y": 3844.4514822843516
          },
          {
            "x": -3866.2691106962748,
            "y": 3844.447808452957
          },
          {
            "x": -3866.7690971990555,
            "y": 3844.4441346215617
          }
        ]
      }
    }
  }
}